converdation/__init__.py
converdation/converter.py
converdation/exceptions.py
converdation/registry.py
converdation/converters/__init__.py
converdation/converters/json_xml.py
converdation/converters/number_base.py
converdation/converters/timestamp_datetime.py
converdation/formatters/__init__.py
converdation/formatters/json_formatter.py
converdation/generators/__init__.py
converdation/generators/lorem_ipsum.py
converdation-0.0.2b0.dist-info/licenses/LICENSE
converdation-0.0.2b0.dist-info/METADATA
converdation-0.0.2b0.dist-info/WHEEL
converdation-0.0.2b0.dist-info/top_level.txt
converdation-0.0.2b0.dist-info/RECORD
