Metadata-Version: 2.4
Name: converdation
Version: 0.0.2b0
Summary: The most essential tools for developers
Author: demshindev
License:                                  Apache License
Project-URL: Homepage, https://demshin.dev/
Project-URL: Repository, https://github.com/demshindev/converdation
Classifier: Development Status :: 4 - Beta
Classifier: Programming Language :: Python :: 3
Classifier: Programming Language :: Python :: 3.9
Classifier: License :: OSI Approved :: Apache Software License
Requires-Python: >=3.9
License-File: LICENSE
Dynamic: license-file
